LICENSE
MANIFEST.in
README.md
setup.py
foamPy.egg-info/PKG-INFO
foamPy.egg-info/SOURCES.txt
foamPy.egg-info/dependency_links.txt
foamPy.egg-info/top_level.txt
foampy/__init__.py
foampy/case.py
foampy/core.py
foampy/dictionaries.py
foampy/foil.py
foampy/gui.py
foampy/templates.py
foampy/types.py
foampy/tests/__init__.py
foampy/tests/test_core.py
foampy/tests/test_dictionaries.py
foampy/tests/test_foil.py
foampy/tests/test_templates.py
foampy/tests/test_types.py
scripts/foampy-gitignore
scripts/foampy-load-surfaces
scripts/foampy-make-template
scripts/foampy-mirror-foildata
scripts/foampy-progress
scripts/foampy-progress-gui
scripts/foampy-reformat-foildata
scripts/pvloadsurf.py