Metadata-Version: 1.1
Name: foamPy
Version: 0.0.5
Summary: Python package for working with OpenFOAM.
Home-page: https://github.com/petebachant/foamPy.git
Author: Pete Bachant
Author-email: petebachant@gmail.com
License: MIT
Platform: UNKNOWN
Classifier: Development Status :: 2 - Pre-Alpha
Classifier: Intended Audience :: Science/Research
Classifier: Natural Language :: English
Classifier: License :: OSI Approved :: MIT License
Classifier: Operating System :: OS Independent
Classifier: Programming Language :: Python
Classifier: Programming Language :: Python :: 2
Classifier: Programming Language :: Python :: 2.6
Classifier: Programming Language :: Python :: 2.7
Classifier: Programming Language :: Python :: 3
Classifier: Programming Language :: Python :: 3.3
Classifier: Topic :: Scientific/Engineering :: Physics
